{
  "locator_domain": "https://www.columbia.com/",
  "location_name": "Snowtrax Alpine Activity Centre & Snowsports Shop",
  "street_address": "Matchams Ln",
  "city": "Christchurch",
  "state": "Dorset",
  "zip": "BH236AW",
  "country_code": "GB",
  "store_number": 92883,
  "phone": "01202 499155",
  "location_type": null,
  "niacs_code": null,
  "latitude": "50.79390832",
  "longitude": "-1.81931298",
  "external_lat_long": false,
  "hours_of_operation": {
    "sun_time_open": 1000,
    "sun_time_close": 1700,
    "mon_time_open": 1000,
    "mon_time_close": 1800,
    "tue_time_open": 1000,
    "tue_time_close": 1800,
    "wed_time_open": 1000,
    "wed_time_close": 1800,
    "thu_time_open": 1000,
    "thu_time_close": 1800,
    "fri_time_open": 1000,
    "fri_time_close": 1800,
    "sat_time_open": 900,
    "sat_time_close": 1800
  }
}