{
  "locator_domain": "https://www.columbia.com/",
  "location_name": "Summit Hut",
  "street_address": "5251 E Speedway Blvd",
  "city": "Tucson",
  "state": "AZ",
  "zip": "85712",
  "country_code": "US",
  "store_number": 427,
  "phone": "(520) 325-1554",
  "location_type": null,
  "niacs_code": null,
  "latitude": "32.23664528",
  "longitude": "-110.88048182",
  "external_lat_long": false,
  "hours_of_operation": {
    "sun_time_open": 900,
    "sun_time_close": 1700,
    "mon_time_open": 900,
    "mon_time_close": 2000,
    "tue_time_open": 900,
    "tue_time_close": 2000,
    "wed_time_open": 900,
    "wed_time_close": 2000,
    "thu_time_open": 900,
    "thu_time_close": 2000,
    "fri_time_open": 900,
    "fri_time_close": 2000,
    "sat_time_open": 900,
    "sat_time_close": 1830
  }
}