{
  "locator_domain": "https://www.columbia.com/",
  "location_name": "Likeys Outdoors",
  "street_address": "2 The Struet",
  "city": "Brecon",
  "state": "",
  "zip": "LD37LH",
  "country_code": "GB",
  "store_number": 104634,
  "phone": "01874 622900",
  "location_type": null,
  "niacs_code": null,
  "latitude": "51.94859851",
  "longitude": "-3.39143556",
  "external_lat_long": false,
  "hours_of_operation": {
    "sun_time_open": 1000,
    "sun_time_close": 1500,
    "mon_time_open": 930,
    "mon_time_close": 1700,
    "tue_time_open": 930,
    "tue_time_close": 1700,
    "wed_time_open": 930,
    "wed_time_close": 1700,
    "thu_time_open": 930,
    "thu_time_close": 1700,
    "fri_time_open": 930,
    "fri_time_close": 1700,
    "sat_time_open": 930,
    "sat_time_close": 1700
  }
}