{
  "locator_domain": "https://www.shopnsavefood.com/",
  "location_name": "Franklin SNS Crosby's Shell",
  "street_address": "151 North 13th St.",
  "city": "Franklin",
  "state": "PA",
  "zip": "16323",
  "country_code": "US",
  "store_number": "277",
  "phone": "0",
  "location_type": {
    "gas_station": "true",
    "active": "true",
    "pump_perk": "true"
  },
  "niacs_code": null,
  "latitude": "41.404710",
  "longitude": "-79.832529",
  "external_lat_long": false,
  "hours_of_operation": null
}