{
  "locator_domain": "https://www.columbia.com/",
  "location_name": "Half-Moon Outfitters",
  "street_address": "425 Coleman Blvd",
  "city": "Mt Pleasant",
  "state": "SC",
  "zip": "29464",
  "country_code": "US",
  "store_number": 18,
  "phone": "(843) 881-9472",
  "location_type": null,
  "niacs_code": null,
  "latitude": "32.79027660",
  "longitude": "-79.87616480",
  "external_lat_long": false,
  "hours_of_operation": {
    "sun_time_open": 1200,
    "sun_time_close": 1800,
    "mon_time_open": 1000,
    "mon_time_close": 1900,
    "tue_time_open": 1000,
    "tue_time_close": 1900,
    "wed_time_open": 1000,
    "wed_time_close": 1900,
    "thu_time_open": 1000,
    "thu_time_close": 1900,
    "fri_time_open": 1000,
    "fri_time_close": 1900,
    "sat_time_open": 1000,
    "sat_time_close": 1900
  }
}