{
  "locator_domain": "https://www.ucbi.com/",
  "location_name": "Lake City Commons",
  "street_address": "255 NW Commons Loop",
  "city": "Lake City",
  "state": "FL",
  "zip": "32055-7700",
  "country_code": "US",
  "store_number": 3488,
  "phone": "3867195446",
  "location_type": null,
  "niacs_code": null,
  "latitude": 30.181497,
  "longitude": -82.664327,
  "external_lat_long": false,
  "hours_of_operation": "Sun 7:00 AM - 10:00 PM,Mon 7:00 AM - 10:00 PM,Tues 7:00 AM - 10:00 PM,Wed 7:00 AM - 10:00 PM,Thurs 7:00 AM - 10:00 PM,Fri 7:00 AM - 10:00 PM,Sat 7:00 AM - 10:00 PM,"
}